tests/__init__.py
tests/settings.py
tests/test_auth.py
tests/test_caching.py
tests/test_getters.py
tests/test_logentry.py
tests/test_templatetags.py
tests/test_urls.py
tests/test_views.py
tests/urls.py
tests/testapp/__init__.py
tests/testapp/apps.py
tests/testapp/models.py
tests/testapp/utils.py
tests/testapp/views.py
useful/__init__.py
useful/attrdict.py
useful/consistent_hash.py
useful/daemontools.py
useful/encoding.py
useful/filelock.py
useful/shortcuts.py
useful/transforms.py
useful/django/__init__.py
useful/django/auth.py
useful/django/cached_auth.py
useful/django/caching.py
useful/django/can_url.py
useful/django/choices.py
useful/django/concurrency.py
useful/django/crypto.py
useful/django/db.py
useful/django/getters.py
useful/django/i18n.py
useful/django/logentry.py
useful/django/readonly_admin.py
useful/django/remote_addr.py
useful/django/urlpatterns.py
useful/django/views.py
useful/django/locale/cs/LC_MESSAGES/django.mo
useful/django/locale/cs/LC_MESSAGES/django.po
useful/django/templatetags/__init__.py
useful/django/templatetags/freshstatic.py
useful/django/templatetags/useful.py
useful-0.8.8.dist-info/LICENSE
useful-0.8.8.dist-info/METADATA
useful-0.8.8.dist-info/WHEEL
useful-0.8.8.dist-info/top_level.txt
useful-0.8.8.dist-info/RECORD
