Metadata-Version: 2.1
Name: useful
Version: 0.8.8
Summary: Everyday use utilities for writing Python code or Django projects.
Home-page: https://github.com/tuttle/python-useful
Author: Vlada Macek
Author-email: macek@sandbox.cz
License: BSD License
Platform: UNKNOWN
Classifier: Development Status :: 5 - Production/Stable
Classifier: Intended Audience :: Developers
Classifier: License :: OSI Approved :: BSD License
Classifier: Operating System :: OS Independent
Classifier: Programming Language :: Python
Classifier: Programming Language :: Python :: 2
Classifier: Programming Language :: Python :: 3
Classifier: Topic :: Software Development :: Libraries
